MANIFEST.in
Products.Andreas09Theme-configure.zcml
README.txt
setup.cfg
setup.py
tests.py
Products/.DS_Store
Products/__init__.py
Products.Andreas09Theme.egg-info/PKG-INFO
Products.Andreas09Theme.egg-info/SOURCES.txt
Products.Andreas09Theme.egg-info/dependency_links.txt
Products.Andreas09Theme.egg-info/entry_points.txt
Products.Andreas09Theme.egg-info/namespace_packages.txt
Products.Andreas09Theme.egg-info/not-zip-safe
Products.Andreas09Theme.egg-info/requires.txt
Products.Andreas09Theme.egg-info/top_level.txt
Products/Andreas09Theme/.DS_Store
Products/Andreas09Theme/__init__.py
Products/Andreas09Theme/configure.zcml
Products/Andreas09Theme/profiles.zcml
Products/Andreas09Theme/setuphandlers.py
Products/Andreas09Theme/skins.zcml
Products/Andreas09Theme/tests.py
Products/Andreas09Theme/version.txt
Products/Andreas09Theme/browser/.DS_Store
Products/Andreas09Theme/browser/__init__.py
Products/Andreas09Theme/browser/configure.zcml
Products/Andreas09Theme/browser/credits_viewlet.pt
Products/Andreas09Theme/browser/footer_viewlet.pt
Products/Andreas09Theme/browser/interfaces.py
Products/Andreas09Theme/browser/logo_modified.pt
Products/Andreas09Theme/browser/portal_title_viewlet.pt
Products/Andreas09Theme/browser/viewlet.pt
Products/Andreas09Theme/browser/viewlets.py
Products/Andreas09Theme/browser/images/README.txt
Products/Andreas09Theme/browser/stylesheets/README.txt
Products/Andreas09Theme/browser/stylesheets/main.css
Products/Andreas09Theme/profiles/default/Products.Andreas09Theme_various.txt
Products/Andreas09Theme/profiles/default/cssregistry.xml
Products/Andreas09Theme/profiles/default/import_steps.xml
Products/Andreas09Theme/profiles/default/jsregistry.xml
Products/Andreas09Theme/profiles/default/metadata.xml
Products/Andreas09Theme/profiles/default/skins.xml
Products/Andreas09Theme/profiles/default/viewlets.xml
Products/Andreas09Theme/skins/.DS_Store
Products/Andreas09Theme/skins/Andreas09Theme_custom_images/CONTENT.txt
Products/Andreas09Theme/skins/Andreas09Theme_custom_images/document_icon.gif
Products/Andreas09Theme/skins/Andreas09Theme_custom_images/favicon.ico
Products/Andreas09Theme/skins/Andreas09Theme_custom_images/file_icon.gif
Products/Andreas09Theme/skins/Andreas09Theme_custom_images/folder_icon.gif
Products/Andreas09Theme/skins/Andreas09Theme_custom_images/search_icon.gif
