Metadata-Version: 1.0
Name: Products.Andreas09Theme
Version: 0.1-step09
Summary: An example theme for Plone 3.0
Home-page: http://pypi.python.org/pypi/Products.Andreas09Theme
Author: David Convent
Author-email: product-developers@lists.plone.org
License: GPL
Keywords: web zope plone theme example tutorial how-to
Platform: UNKNOWN
Classifier: Framework :: Plone
Classifier: Programming Language :: Python
Classifier: Topic :: Software Development :: Libraries :: Python Modules
